hydra_plugins/sheeprl_search_path.py
sheeprl/__init__.py
sheeprl/__main__.py
sheeprl/available_agents.py
sheeprl/cli.py
sheeprl/algos/__init__.py
sheeprl/algos/a2c/__init__.py
sheeprl/algos/a2c/a2c.py
sheeprl/algos/a2c/agent.py
sheeprl/algos/a2c/evaluate.py
sheeprl/algos/a2c/loss.py
sheeprl/algos/a2c/utils.py
sheeprl/algos/dreamer_v1/__init__.py
sheeprl/algos/dreamer_v1/agent.py
sheeprl/algos/dreamer_v1/dreamer_v1.py
sheeprl/algos/dreamer_v1/evaluate.py
sheeprl/algos/dreamer_v1/loss.py
sheeprl/algos/dreamer_v1/utils.py
sheeprl/algos/dreamer_v2/__init__.py
sheeprl/algos/dreamer_v2/agent.py
sheeprl/algos/dreamer_v2/dreamer_v2.py
sheeprl/algos/dreamer_v2/evaluate.py
sheeprl/algos/dreamer_v2/loss.py
sheeprl/algos/dreamer_v2/utils.py
sheeprl/algos/dreamer_v3/__init__.py
sheeprl/algos/dreamer_v3/agent.py
sheeprl/algos/dreamer_v3/dreamer_v3.py
sheeprl/algos/dreamer_v3/evaluate.py
sheeprl/algos/dreamer_v3/loss.py
sheeprl/algos/dreamer_v3/utils.py
sheeprl/algos/droq/__init__.py
sheeprl/algos/droq/agent.py
sheeprl/algos/droq/droq.py
sheeprl/algos/droq/evaluate.py
sheeprl/algos/droq/utils.py
sheeprl/algos/p2e_dv1/__init__.py
sheeprl/algos/p2e_dv1/agent.py
sheeprl/algos/p2e_dv1/evaluate.py
sheeprl/algos/p2e_dv1/p2e_dv1_exploration.py
sheeprl/algos/p2e_dv1/p2e_dv1_finetuning.py
sheeprl/algos/p2e_dv1/utils.py
sheeprl/algos/p2e_dv2/__init__.py
sheeprl/algos/p2e_dv2/agent.py
sheeprl/algos/p2e_dv2/evaluate.py
sheeprl/algos/p2e_dv2/p2e_dv2_exploration.py
sheeprl/algos/p2e_dv2/p2e_dv2_finetuning.py
sheeprl/algos/p2e_dv2/utils.py
sheeprl/algos/p2e_dv3/__init__.py
sheeprl/algos/p2e_dv3/agent.py
sheeprl/algos/p2e_dv3/evaluate.py
sheeprl/algos/p2e_dv3/p2e_dv3_exploration.py
sheeprl/algos/p2e_dv3/p2e_dv3_finetuning.py
sheeprl/algos/p2e_dv3/utils.py
sheeprl/algos/ppo/__init__.py
sheeprl/algos/ppo/agent.py
sheeprl/algos/ppo/evaluate.py
sheeprl/algos/ppo/loss.py
sheeprl/algos/ppo/ppo.py
sheeprl/algos/ppo/ppo_decoupled.py
sheeprl/algos/ppo/utils.py
sheeprl/algos/ppo_recurrent/__init__.py
sheeprl-0.5.7.dist-info/LICENSE
sheeprl-0.5.7.dist-info/METADATA
sheeprl-0.5.7.dist-info/WHEEL
sheeprl-0.5.7.dist-info/entry_points.txt
sheeprl-0.5.7.dist-info/top_level.txt
sheeprl-0.5.7.dist-info/RECORD
