Metadata-Version: 2.1
Name: sheeprl
Version: 0.5.7
Summary: High-quality, single file and distributed implementation of Deep Reinforcement Learning algorithms with production-friendly features
Author-email: Federico Belotti <federico.belotti@orobix.com>, Davide Angioni <davide.angioni@orobix.com>, Refik Can Malli <refikcan.malli@orobix.com>, Michele Milesi <michele.milesi@orobix.com>
Maintainer-email: Federico Belotti <federico.belotti@orobix.com>, Davide Angioni <davide.angioni@orobix.com>, Refik Can Malli <refikcan.malli@orobix.com>, Michele Milesi <michele.milesi@orobix.com>
License: Apache License
Project-URL: homepage, https://eclecticsheep.ai
Project-URL: repository, https://github.com/Eclectic-Sheep/sheeprl
Keywords: reinforcement,machine,learning,distributed,production
Classifier: Programming Language :: Python
Classifier: Topic :: Scientific/Engineering :: Artificial Intelligence
Requires-Python: <3.12,>=3.8
License-File: LICENSE
Requires-Dist: gymnasium ==0.29.*
Requires-Dist: pygame >=2.1.3
Requires-Dist: moviepy >=1.0.3
Requires-Dist: tensorboard >=2.10
Requires-Dist: python-dotenv >=1.0.0
Requires-Dist: lightning >=2.0
Requires-Dist: lightning-utilities <=0.9
Requires-Dist: hydra-core ==1.3.0
Requires-Dist: torchmetrics
Requires-Dist: rich ==13.5.*
Requires-Dist: opencv-python ==4.8.0.*
Requires-Dist: torch !=2.2.0,>=2.0
Provides-Extra: atari
Requires-Dist: gymnasium[atari] ==0.29.* ; extra == 'atari'
Requires-Dist: gymnasium[accept-rom-license] ==0.29.* ; extra == 'atari'
Requires-Dist: gymnasium[other] ==0.29.* ; extra == 'atari'
Provides-Extra: box2d
Requires-Dist: gymnasium[box2d] ==0.29.* ; extra == 'box2d'
Provides-Extra: crafter
Requires-Dist: crafter ==1.8.3 ; extra == 'crafter'
Provides-Extra: dev
Requires-Dist: pre-commit ==3.5.0 ; extra == 'dev'
Requires-Dist: mypy ==1.2.0 ; extra == 'dev'
Requires-Dist: black ==23.12.1 ; extra == 'dev'
Requires-Dist: isort ==5.13.2 ; extra == 'dev'
Requires-Dist: autoflake ==2.2.1 ; extra == 'dev'
Requires-Dist: ruff ==0.1.11 ; extra == 'dev'
Provides-Extra: diambra
Requires-Dist: diambra ==0.0.17 ; extra == 'diambra'
Requires-Dist: diambra-arena ==2.2.6 ; extra == 'diambra'
Provides-Extra: dmc
Requires-Dist: dm-control >=1.0.12 ; extra == 'dmc'
Provides-Extra: minedojo
Requires-Dist: minedojo ==0.1 ; extra == 'minedojo'
Requires-Dist: importlib-resources ==5.12.0 ; extra == 'minedojo'
Requires-Dist: gym ==0.21.0 ; extra == 'minedojo'
Provides-Extra: minerl
Requires-Dist: setuptools ==66.0.0 ; extra == 'minerl'
Requires-Dist: minerl ==0.4.4 ; extra == 'minerl'
Requires-Dist: gym ==0.19.0 ; extra == 'minerl'
Provides-Extra: mlflow
Requires-Dist: mlflow ==2.11.1 ; extra == 'mlflow'
Provides-Extra: mujoco
Requires-Dist: mujoco >=2.3.3 ; extra == 'mujoco'
Requires-Dist: gymnasium[mujoco] ==0.29.* ; extra == 'mujoco'
Provides-Extra: supermario
Requires-Dist: gym-super-mario-bros ==7.4.0 ; extra == 'supermario'
Requires-Dist: gym <0.26 ; extra == 'supermario'
Provides-Extra: test
Requires-Dist: pytest ==7.3.1 ; extra == 'test'
Requires-Dist: pytest-timeout ==2.1.0 ; extra == 'test'
Requires-Dist: pytest-coverage ; extra == 'test'
Requires-Dist: importlib-resources >=6.2.0 ; extra == 'test'
